odoo/addons/shopinvader_locomotive_sale_profile/README.rst
odoo/addons/shopinvader_locomotive_sale_profile/__init__.py
odoo/addons/shopinvader_locomotive_sale_profile/__manifest__.py
odoo/addons/shopinvader_locomotive_sale_profile/components/__init__.py
odoo/addons/shopinvader_locomotive_sale_profile/components/shopinvader_sale_profile_listener.py
odoo/addons/shopinvader_locomotive_sale_profile/readme/CONTRIBUTORS.rst
odoo/addons/shopinvader_locomotive_sale_profile/readme/DESCRIPTION.rst
odoo/addons/shopinvader_locomotive_sale_profile/static/description/index.html
odoo/addons/shopinvader_locomotive_sale_profile/tests/__init__.py
odoo/addons/shopinvader_locomotive_sale_profile/tests/test_shopinvader_partner.py
odoo13_addon_shopinvader_locomotive_sale_profile-13.0.1.2.0.dist-info/METADATA
odoo13_addon_shopinvader_locomotive_sale_profile-13.0.1.2.0.dist-info/WHEEL
odoo13_addon_shopinvader_locomotive_sale_profile-13.0.1.2.0.dist-info/top_level.txt
odoo13_addon_shopinvader_locomotive_sale_profile-13.0.1.2.0.dist-info/RECORD
