Metadata-Version: 2.1
Name: odoo13-addon-shopinvader-locomotive-sale-profile
Version: 13.0.1.2.0
Summary: Synchronize the sale profile info to customer record on Locomotive
Home-page: https://github.com/shopinvader/odoo-shopinvader
Author: Akretion,Camptocamp
License: AGPL-3
Platform: UNKNOWN
Classifier: Programming Language :: Python
Classifier: Framework :: Odoo
Classifier: License :: OSI Approved :: GNU Affero General Public License v3
Requires-Python: >=3.5
Requires-Dist: odoo13-addon-shopinvader-locomotive
Requires-Dist: odoo13-addon-shopinvader-sale-profile
Requires-Dist: odoo (<13.1dev,>=13.0a)
